rockethub/__init__.py
rockethub/discovery_api.py
rockethub/rocket.py
rockethub-0.1.1.dist-info/LICENSE.txt
rockethub-0.1.1.dist-info/METADATA
rockethub-0.1.1.dist-info/WHEEL
rockethub-0.1.1.dist-info/top_level.txt
rockethub-0.1.1.dist-info/RECORD
