Metadata-Version: 2.1
Name: rockethub
Version: 0.1.1
Summary: Accelerating Machine Learning Research
Home-page: https://rockethub.ai
Author: Mirage Technologies AG
Author-email: hello@mirage.id
License: Proprietary
Keywords: Automating,ML,Research
Platform: UNKNOWN
Classifier: Development Status :: 2 - Pre-Alpha
Classifier: Intended Audience :: Developers
Classifier: Topic :: Software Development :: Build Tools
Classifier: Programming Language :: Python :: 3
Classifier: Programming Language :: Python :: 3.4
Classifier: Programming Language :: Python :: 3.5
Classifier: Programming Language :: Python :: 3.6
Requires-Dist: tqdm
Requires-Dist: requests
